MANIFEST.in
README.md
setup.py
pycyt/__init__.py
pycyt/data.py
pycyt/scale.py
pycyt/util.py
pycyt/version.py
pycyt.egg-info/PKG-INFO
pycyt.egg-info/SOURCES.txt
pycyt.egg-info/dependency_links.txt
pycyt.egg-info/requires.txt
pycyt.egg-info/top_level.txt