Metadata-Version: 1.1
Name: pycyt
Version: 0.0.1
Summary: Python package for the analysis of flow cytometry data
Home-page: https://github.com/jlumpe/pycyt
Author: Jared Lumpe
Author-email: mjlumpe@gmail.com
License: UNKNOWN
Platform: UNKNOWN
Classifier: Development Status :: 2 - Pre-Alpha
Classifier: Intended Audience :: Developers
Classifier: Intended Audience :: Science/Research
Classifier: Operating System :: OS Independent
Classifier: Programming Language :: Python :: 3
Classifier: Programming Language :: Python :: 3.5
Classifier: Programming Language :: Python :: 3.6
Classifier: Topic :: Scientific/Engineering
Classifier: Topic :: Scientific/Engineering :: Bio-Informatics
